drl_wizard/__init__.py
drl_wizard/cli.py
drl_wizard/algorithms/__init__.py
drl_wizard/algorithms/algos/__init__.py
drl_wizard/algorithms/algos/a2c_algo/__init__.py
drl_wizard/algorithms/algos/a2c_algo/actor_critic.py
drl_wizard/algorithms/algos/a2c_algo/policy.py
drl_wizard/algorithms/algos/a2c_algo/trainer.py
drl_wizard/algorithms/algos/a2c_algo/network/__init__.py
drl_wizard/algorithms/algos/a2c_algo/network/act_layer.py
drl_wizard/algorithms/algos/a2c_algo/network/cnn.py
drl_wizard/algorithms/algos/a2c_algo/network/distributions.py
drl_wizard/algorithms/algos/a2c_algo/network/mlp.py
drl_wizard/algorithms/algos/dqn_algo/__init__.py
drl_wizard/algorithms/algos/dqn_algo/actor.py
drl_wizard/algorithms/algos/dqn_algo/policy.py
drl_wizard/algorithms/algos/dqn_algo/trainer.py
drl_wizard/algorithms/algos/dqn_algo/network/__init__.py
drl_wizard/algorithms/algos/dqn_algo/network/act_layer.py
drl_wizard/algorithms/algos/dqn_algo/network/cnn.py
drl_wizard/algorithms/algos/dqn_algo/network/distributions.py
drl_wizard/algorithms/algos/dqn_algo/network/mlp.py
drl_wizard/algorithms/algos/ppo_algo/__init__.py
drl_wizard/algorithms/algos/ppo_algo/actor_critic.py
drl_wizard/algorithms/algos/ppo_algo/policy.py
drl_wizard/algorithms/algos/ppo_algo/trainer.py
drl_wizard/algorithms/algos/ppo_algo/network/__init__.py
drl_wizard/algorithms/algos/ppo_algo/network/act_layer.py
drl_wizard/algorithms/algos/ppo_algo/network/cnn.py
drl_wizard/algorithms/algos/ppo_algo/network/distributions.py
drl_wizard/algorithms/algos/ppo_algo/network/mlp.py
drl_wizard/algorithms/algos/sac_algo/__init__.py
drl_wizard/algorithms/algos/sac_algo/actor_q.py
drl_wizard/algorithms/algos/sac_algo/policy.py
drl_wizard/algorithms/algos/sac_algo/trainer.py
drl_wizard/algorithms/algos/sac_algo/network/__init__.py
drl_wizard/algorithms/algos/sac_algo/network/act_layer.py
drl_wizard/algorithms/algos/sac_algo/network/cnn.py
drl_wizard/algorithms/algos/sac_algo/network/distributions.py
drl_wizard-0.1.3.dist-info/METADATA
drl_wizard-0.1.3.dist-info/WHEEL
drl_wizard-0.1.3.dist-info/entry_points.txt
drl_wizard-0.1.3.dist-info/top_level.txt
drl_wizard-0.1.3.dist-info/RECORD
